{
  "hyperlinks": {
    "facebook": "https://www.facebook.com/maxpatelmusic/",
    "twitter": "https://twitter.com/MaxPatel_Music",
    "instagram": "https://www.instagram.com/maxpatelmusic/",
    "spotify": "https://open.spotify.com/artist/3HcJd4UuaOq2pVginUi5MY",
    "youtube": "https://www.youtube.com/channel/UCPtjLE0quEXBH3GH7Kk9m_g",
    "soundcloud": "https://soundcloud.com/maximilian-patel"
  },
  "jayaniEmail": "jayanitunes@gmail.com",
  "merchHyperlink": "https://google.com",
  "progressionsLinks": {
    "spotify": "https://open.spotify.com/album/7wgqIStm5JdekbVrRAiJLG?si=6pP3y82dSxikuHNT-jdqXw",
    "soundcloud": "https://soundcloud.com/maximilian-patel/sets/progressions-ep",
    "apple": "https://itunes.apple.com/us/album/progressions-ep/1311200831",
    "tidal": "https://tidal.com/album/81121467",
    "amazon": "http://a.co/83opEWU",
    "google": "https://play.google.com/store/music/album/Max_Patel_Progressions?id=Bqfachws5alrah5mnlsyzxrywfm&hl=en",
    "deezer": "https://www.deezer.com/album/51492902?utm_source=deezer&utm_content=album-51492902&utm_term=2199278564_1534121446&utm_medium=web"
  },
  "progressionsSpotify": "https://open.spotify.com/embed/album/7wgqIStm5JdekbVrRAiJLG",
  "solipsismLinks": {
    "spotify": "https://open.spotify.com/album/4yFI00Or7s33LWrlMV5JCp?si=1Ys1OGTBRwi-Olj4QPzBXQ",
    "soundcloud": "https://soundcloud.com/maximilian-patel/solopsism",
    "apple": "https://itunes.apple.com/us/album/solipsism/1272991234?i=1272991238",
    "tidal": "https://tidal.com/album/77575584",
    "amazon": "http://a.co/fOrBzJ2",
    "google": "https://play.google.com/store/music/album/Max_Patel_Solipsism?id=Bproqzzzt4myq4iz2a3npfnykaq&hl=en",
    "deezer": "https://www.deezer.com/album/46547262?utm_source=deezer&utm_content=album-46547262&utm_term=2199278564_1534122453&utm_medium=web"
  },
  "solipsismSpotify": "https://open.spotify.com/embed/album/4yFI00Or7s33LWrlMV5JCp"
}